[
  {
    "id": 1,
    "name": "Термостат",
    "oe": "2700180900",
    "brand": "Mercedes-Benz",
    "stock": 85,
    "image": "fenlei-chanp-jpg/奔驰/冷却系统/节温器/进气管、水箱装配盘系列/2700180900:61.6*27.7cm:144g/DSC06306.jpg"
  },
  {
    "id": 2,
    "name": "Насос ГУР",
    "oe": "0064666401",
    "brand": "Mercedes-Benz",
    "stock": 75,
    "image": "fenlei-chanp-jpg/奔驰/转向系统/转向助力泵/助力泵系列/0064666401:33*24*19cm:2742.5g/DSC04187.jpg"
  },
  {
    "id": 3,
    "name": "Шланг радиатора",
    "oe": "13717582312",
    "brand": "BMW",
    "stock": 95,
    "image": "fenlei-chanp-jpg/宝马/冷却系统/节温器/进气管、水箱装配盘系列/13717582312D:38*25cm:195g/DSC06210.jpg"
  },
  {
    "id": 4,
    "name": "Впускной коллектор",
    "oe": "2721402401",
    "brand": "Mercedes-Benz",
    "stock": 120,
    "image": "fenlei-chanp-jpg/奔驰/进气排气系统/进气歧管/进气支管、修包系列/2721402401:47*40.5*30.5cm:6540.5g/DSC01987.jpg"
  },
  {
    "id": 5,
    "name": "Дроссельная заслонка",
    "oe": "13547506627",
    "brand": "BMW",
    "stock": 110,
    "image": "fenlei-chanp-jpg/宝马/进气排气系统/进气歧管/节气门系列/13547506627:18*14.5*14.5cm:1316.0g/DSC08047.jpg"
  }
]